[
  {
    "image": "20190907_bakabon.jpg",
    "description": "馬鹿坊（大阪，中崎町）：ドロ坦々まぜそば"
  },
  {
    "image": "20190902_issaku.jpg",
    "description": "一作（大阪，南茨木）：こってりラーメン"
  },
  {
    "image": "20190901_gunjo.jpg",
    "description": "群青（大阪，天神橋筋六丁目）：つけめん３代目"
  },
  {
    "image": "20190825_toudai.jpg",
    "description": "ラーメン東大（京都，京都駅）：徳島ラーメン"
  },
  {
    "image": "20190816_seaburanokami.jpg",
    "description": "セアブラノ神（京都，四条大宮）"
  },
  {
    "image": "20190720_hayato.jpg",
    "description": "颯人（大阪，南森町）"
  },
  {
    "image": "20190718_tokkari.jpg",
    "description": "とっかり（大阪，茨木）"
  },
  {
    "image": "20190715_ennosuke.jpg",
    "description": "縁乃助商店（大阪，淡路）"
  },
  {
    "image": "20190623_kanbannai.jpg",
    "description": "名もなきラーメン屋（京都，三条）"
  },
  {
    "image": "20190607_sankichiya.jpg",
    "description": "三吉屋（新潟）"
  },
  {
    "image": "20190607_yabusoba.jpg",
    "description": "薮そば（新潟）"
  },
  {
    "image": "20190605_ittouya.jpg",
    "description": "いっとうや（新潟）"
  },
  {
    "image": "20190530_sin.jpg",
    "description": "らーめん真（大阪，茨木）"
  },
  {
    "image": "20190520_takamatuya.jpg",
    "description": "麺匠たか松（京都，烏丸）"
  },
  {
    "image": "20190520_enaku.jpg",
    "description": "つけ麺恵那く（京都一乗寺）：カレーつけめん"
  },
  {
    "image": "20190517_sugawarawas.jpg",
    "description": "NAKAGAWAわず（大阪，淡路）"
  },
  {
    "image": "20190428_sugari.jpg",
    "description": "和醸良麺すがり（京都，四条）"
  },
  {
    "image": "20190421_touhichi.jpg",
    "description": "らぁ麺とうひち（京都，北大路）"
  },
  {
    "image": "20190318_ichigen.jpg",
    "description": "一幻（北海道，すすきの）：えびしお（そのまま）"
  },
  {
    "image": "20190318_samurai.jpg",
    "description": ""
  },
  {
    "image": "20190318_yukikaze.jpg",
    "description": ""
  },
  {
    "image": "20190313_hanabi.jpg",
    "description": ""
  },
  {
    "image": "20190306_enaku.jpg",
    "description": ""
  },
  {
    "image": "20190306_gokkei.jpg",
    "description": ""
  },
  {
    "image": "20190305_seven.jpg",
    "description": ""
  },
  {
    "image": "20190221_moeyomensuke.jpg",
    "description": ""
  },
  {
    "image": "20190217_mutahiro.jpg",
    "description": ""
  },
  {
    "image": "20190217_zagin.jpg",
    "description": ""
  },
  {
    "image": "20190210_domannaka.jpg",
    "description": ""
  },
  {
    "image": "20190204_ohno.jpg",
    "description": ""
  },
  {
    "image": "20190114_jet.jpg",
    "description": ""
  },
  {
    "image": "20181214_ushio.jpg",
    "description": ""
  },
  {
    "image": "20181125_sanku.jpg",
    "description": ""
  },
  {
    "image": "20181117_shiina.jpg",
    "description": ""
  },
  {
    "image": "20181113_kinsei.jpg",
    "description": ""
  },
  {
    "image": "20181104_ennnosuke.jpg",
    "description": ""
  },
  {
    "image": "20181028_ikkei.jpg",
    "description": ""
  },
  {
    "image": "20181014_ramendarbie.jpg",
    "description": ""
  },
  {
    "image": "20181014_zagin.jpg",
    "description": ""
  },
  {
    "image": "20181008_ramendarbie.jpg",
    "description": ""
  },
  {
    "image": "20180930_keiji.jpg",
    "description": ""
  },
  {
    "image": "20180928_kaiji.jpg",
    "description": ""
  },
  {
    "image": "20180920_kai.jpg",
    "description": ""
  },
  {
    "image": "20180912_anoramen.jpg",
    "description": ""
  },
  {
    "image": "20180909_mushin.jpg",
    "description": ""
  },
  {
    "image": "20180908_mitsuba.jpg",
    "description": ""
  },
  {
    "image": "20180907_miso.jpg",
    "description": ""
  },
  {
    "image": "20180903_mario.jpg",
    "description": ""
  },
  {
    "image": "20180902_chidoru.jpg",
    "description": ""
  },
  {
    "image": "20180901_noroma.jpg",
    "description": ""
  },
  {
    "image": "20180901_barom.jpg",
    "description": ""
  },
  {
    "image": "20180826_fujimon.jpg",
    "description": ""
  },
  {
    "image": "20180826_sakura.jpg",
    "description": ""
  },
  {
    "image": "20180825_fukukitaru.jpg",
    "description": ""
  },
  {
    "image": "20180715_inoichi.jpg",
    "description": ""
  },
  {
    "image": "20180714_toyamablack.jpg",
    "description": ""
  },
  {
    "image": "20180701_yasube.jpg",
    "description": ""
  },
  {
    "image": "20180701_bokkosi.jpg",
    "description": ""
  },
  {
    "image": "20180701_tensinya.jpg",
    "description": ""
  },
  {
    "image": "20180519_boogie.jpg",
    "description": ""
  },
  {
    "image": "20180513_akamon.jpg",
    "description": ""
  },
  {
    "image": "20180504_bokkosi.jpg",
    "description": ""
  },
  {
    "image": "20180120_gokkei.jpg",
    "description": ""
  },
  {
    "image": "20180106_kadoya.jpg",
    "description": ""
  },
  {
    "image": "20171217_oyamaya.jpg",
    "description": ""
  },
  {
    "image": "20171217_domiso.jpg",
    "description": ""
  },
  {
    "image": "20171203_youji.jpg",
    "description": ""
  },
  {
    "image": "20171123_masutani.jpg",
    "description": ""
  },
  {
    "image": "20171119_hanabi.jpg",
    "description": ""
  },
  {
    "image": "20171119_misen.jpg",
    "description": ""
  },
  {
    "image": "20171118_yabaton.jpg",
    "description": ""
  },
  {
    "image": "20171114_kusooyaji.jpg",
    "description": ""
  },
  {
    "image": "20171015_toudai.jpg",
    "description": ""
  },
  {
    "image": "20171014_joroku.jpg",
    "description": ""
  },
  {
    "image": "20171014_junkstory.jpg",
    "description": ""
  },
  {
    "image": "20171008_tikyuukibo.jpg",
    "description": ""
  },
  {
    "image": "20171008_menmichi.jpg",
    "description": ""
  },
  {
    "image": "20171008_touka.jpg",
    "description": ""
  }
]